horbach_cli/README.md
horbach_cli/__init__.py
horbach_cli/converter.py
horbach_cli/deduplicator.py
horbach_cli/libs/__init__.py
horbach_cli/libs/common.py
horbach_cli/libs/common_xsh.xsh
horbach_cli/libs/converter.py
horbach_cli/main.py
horbach_cli/warp.xsh
horbach_cli-0.3.0.dist-info/METADATA
horbach_cli-0.3.0.dist-info/WHEEL
horbach_cli-0.3.0.dist-info/entry_points.txt
horbach_cli-0.3.0.dist-info/RECORD
